odoo/addons/sale_mrp_bom_menu/README.rst
odoo/addons/sale_mrp_bom_menu/__init__.py
odoo/addons/sale_mrp_bom_menu/__manifest__.py
odoo/addons/sale_mrp_bom_menu/i18n/it.po
odoo/addons/sale_mrp_bom_menu/i18n/sale_mrp_bom_menu.pot
odoo/addons/sale_mrp_bom_menu/readme/CONTRIBUTORS.md
odoo/addons/sale_mrp_bom_menu/readme/DESCRIPTION.md
odoo/addons/sale_mrp_bom_menu/static/description/icon.png
odoo/addons/sale_mrp_bom_menu/static/description/index.html
odoo/addons/sale_mrp_bom_menu/views/menu.xml
odoo_addon_sale_mrp_bom_menu-18.0.1.0.0.4.dist-info/METADATA
odoo_addon_sale_mrp_bom_menu-18.0.1.0.0.4.dist-info/WHEEL
odoo_addon_sale_mrp_bom_menu-18.0.1.0.0.4.dist-info/top_level.txt
odoo_addon_sale_mrp_bom_menu-18.0.1.0.0.4.dist-info/RECORD
